jrenderer/__init__.py
jrenderer/brax_adaptor.py
jrenderer/brax_adaptor_with_cliping.py
jrenderer/camera.py
jrenderer/camera_linker.py
jrenderer/capsule.py
jrenderer/cube.py
jrenderer/lights.py
jrenderer/model.py
jrenderer/pipeline.py
jrenderer/pipeline_brax.py
jrenderer/pipeline_brax_without_clipping.py
jrenderer/plane.py
jrenderer/r_types.py
jrenderer/scene.py
jrenderer/shader.py
jrenderer/util_functions.py
jrenderer-1.1.dist-info/LICENSE
jrenderer-1.1.dist-info/METADATA
jrenderer-1.1.dist-info/WHEEL
jrenderer-1.1.dist-info/top_level.txt
jrenderer-1.1.dist-info/RECORD
